plutus_pairtrading/__init__.py
plutus_pairtrading/data_acquisitions/__init__.py
plutus_pairtrading/data_acquisitions/data_acquisition.py
plutus_pairtrading/data_generations/__init__.py
plutus_pairtrading/data_generations/data_generation.py
plutus_pairtrading/data_visualizations/__init__.py
plutus_pairtrading/data_visualizations/plots.py
plutus_pairtrading/tests/__init__.py
plutus_pairtrading/tests/cointegration_tests.py
plutus_pairtrading/tests/stationarity_tests.py
plutus_pairtrading/utils/__init__.py
plutus_pairtrading/utils/performance.py
plutus_pairtrading-1.1.1.dist-info/LICENSE
plutus_pairtrading-1.1.1.dist-info/METADATA
plutus_pairtrading-1.1.1.dist-info/WHEEL
plutus_pairtrading-1.1.1.dist-info/RECORD
